art/__init__.py
art/checks.py
art/core.py
art/decorators.py
art/loggers.py
art/metrics.py
art/project.py
art/steps.py
art/cli/__init__.py
art/cli/__main__.py
art/cli/main.py
art/cli/utils.py
art/dashboard/__init__.py
art/dashboard/app.py
art/dashboard/backend.py
art/dashboard/const.py
art/dashboard/help.py
art/dashboard/layout.py
art/dashboard/timeline.py
art/utils/__init__.py
art/utils/enums.py
art/utils/exceptions.py
art/utils/paths.py
art/utils/quickstart.py
art/utils/savers.py
docs/source/conf.py
art_training-1.0.0.dist-info/METADATA
art_training-1.0.0.dist-info/WHEEL
art_training-1.0.0.dist-info/licenses/LICENCE
art_training-1.0.0.dist-info/RECORD
