Metadata-Version: 2.1
Name: art-training
Version: 1.0.0
Summary: ART - Actually Robust Training framework - a framework that teaches good practices when training deep neural networks. 
Project-URL: Homepage, https://github.com/sebchw/art
Project-URL: Bug Tracker, https://github.com/sebchw/art/issues
Author-email: Sebastian Chwilczynski <sebastian.chwilczynski@student.put.poznan.pl>, Kacper Trebacz <kacper.trebacz@student.put.poznan.pl>, Mateusz Malecki <mateusz.malecki.1@student.put.poznan.pl>, Karol Cyganik <karol.cyganik@student.put.poznan.pl>
License-File: LICENCE
Keywords: deep learning,framework,pytorch,training
Classifier: License :: OSI Approved :: MIT License
Classifier: Operating System :: OS Independent
Classifier: Programming Language :: Python :: 3
Requires-Python: >=3.10
Requires-Dist: cookiecutter>=2.3.1
Requires-Dist: datasets>=2.11.0
Requires-Dist: lightning>=1.9
Requires-Dist: loguru==0.7.2
Requires-Dist: matplotlib~=3.6
Requires-Dist: pygithub==2.1.1
Requires-Dist: torch>=1.13.1
Requires-Dist: typer==0.4.2
Provides-Extra: dashboard
Requires-Dist: dash; extra == 'dashboard'
Requires-Dist: dash-bootstrap-components; extra == 'dashboard'
Requires-Dist: dash-mantine-components; extra == 'dashboard'
Requires-Dist: plotly; extra == 'dashboard'
Provides-Extra: dev
Requires-Dist: black>=23.1.0; extra == 'dev'
Requires-Dist: flake8>=6.0.0; extra == 'dev'
Requires-Dist: ipykernel>=6.26.0; extra == 'dev'
Requires-Dist: mypy>=1.1.1; extra == 'dev'
Requires-Dist: myst-nb==0.17.2; extra == 'dev'
Requires-Dist: nbconvert>=7.9.2; extra == 'dev'
Requires-Dist: pytest-cov>=4.0.0; extra == 'dev'
Requires-Dist: pytest>=7.2.2; extra == 'dev'
Requires-Dist: sphinx-autodoc2==0.4.2; extra == 'dev'
Requires-Dist: tox>=4.4.7; extra == 'dev'
